<?xml version="1.0"?>

<portlet-app xmlns="http://java.sun.com/xml/ns/portlet/portlet-app_2_0.xsd" xmlns:xsi="http://www.w3.org/2001/XMLSchema-instance" xsi:schemaLocation="http://java.sun.com/xml/ns/portlet/portlet-app_2_0.xsd http://java.sun.com/xml/ns/portlet/portlet-app_2_0.xsd" version="2.0">
	<portlet>
		<portlet-name>Demo</portlet-name>
		<display-name>Demo</display-name>
		<portlet-class>com.liferay.util.bridges.mvc.MVCPortlet</portlet-class>
		<init-param>
			<name>view-template</name>
			<value>/view.jsp</value>
		</init-param>
		<expiration-cache>0</expiration-cache>
		<supports>
			<mime-type>text/html</mime-type>
		</supports>
		<portlet-info>
			<title>Demo</title>
			<short-title>Demo</short-title>
			<keywords>Demo</keywords>
		</portlet-info>
		<security-role-ref>
			<role-name>administrator</role-name>
		</security-role-ref>
		<security-role-ref>
			<role-name>guest</role-name>
		</security-role-ref>
		<security-role-ref>
			<role-name>power-user</role-name>
		</security-role-ref>
		<security-role-ref>
			<role-name>user</role-name>
		</security-role-ref>
	</portlet>
	<portlet>
		<portlet-name>first</portlet-name>
		<display-name>First</display-name>
		<portlet-class>com.test.FirstPortlet</portlet-class>
		<init-param>
			<name>view-template</name>
			<value>/html/first/view.jsp</value>
		</init-param>
		<expiration-cache>0</expiration-cache>
		<supports>
			<mime-type>text/html</mime-type>
			<portlet-mode>view</portlet-mode>
		</supports>
		<portlet-info>
			<title>First</title>
			<short-title>First</short-title>
			<keywords></keywords>
		</portlet-info>
		<security-role-ref>
			<role-name>administrator</role-name>
		</security-role-ref>
		<security-role-ref>
			<role-name>guest</role-name>
		</security-role-ref>
		<security-role-ref>
			<role-name>power-user</role-name>
		</security-role-ref>
		<security-role-ref>
			<role-name>user</role-name>
		</security-role-ref>
	</portlet>
	<portlet>
		<portlet-name>send</portlet-name>
		<display-name>Send</display-name>
		<portlet-class>com.test.SendPortlet</portlet-class>
		<init-param>
			<name>view-template</name>
			<value>/html/send/view.jsp</value>
		</init-param>
		<expiration-cache>0</expiration-cache>
		<supports>
			<mime-type>text/html</mime-type>
			<portlet-mode>view</portlet-mode>
		</supports>
		<portlet-info>
			<title>Send</title>
			<short-title>Send</short-title>
			<keywords></keywords>
		</portlet-info>
		<security-role-ref>
			<role-name>administrator</role-name>
		</security-role-ref>
		<security-role-ref>
			<role-name>guest</role-name>
		</security-role-ref>
		<security-role-ref>
			<role-name>power-user</role-name>
		</security-role-ref>
		<security-role-ref>
			<role-name>user</role-name>
		</security-role-ref>
	</portlet>
	<portlet>
		<portlet-name>receive</portlet-name>
		<display-name>Receive</display-name>
		<portlet-class>com.test.ReceivePortlet</portlet-class>
		<init-param>
			<name>view-template</name>
			<value>/html/receive/view.jsp</value>
		</init-param>
		<expiration-cache>0</expiration-cache>
		<supports>
			<mime-type>text/html</mime-type>
			<portlet-mode>view</portlet-mode>
		</supports>
		<portlet-info>
			<title>Receive</title>
			<short-title>Receive</short-title>
			<keywords></keywords>
		</portlet-info>
		<security-role-ref>
			<role-name>administrator</role-name>
		</security-role-ref>
		<security-role-ref>
			<role-name>guest</role-name>
		</security-role-ref>
		<security-role-ref>
			<role-name>power-user</role-name>
		</security-role-ref>
		<security-role-ref>
			<role-name>user</role-name>
		</security-role-ref>
	</portlet>
	<portlet>
		<portlet-name>student-mvc-portlet-action</portlet-name>
		<display-name>Student Mvc Portlet Action</display-name>
		<portlet-class>com.test.StudentMVCPortletAction</portlet-class>
		<init-param>
			<name>view-template</name>
			<value>/html/studentmvcportletaction/view.jsp</value>
		</init-param>
		<expiration-cache>0</expiration-cache>
		<supports>
			<mime-type>text/html</mime-type>
			<portlet-mode>view</portlet-mode>
		</supports>
		<portlet-info>
			<title>Student Mvc Portlet Action</title>
			<short-title>Student Mvc Portlet Action</short-title>
			<keywords></keywords>
		</portlet-info>
		<security-role-ref>
			<role-name>administrator</role-name>
		</security-role-ref>
		<security-role-ref>
			<role-name>guest</role-name>
		</security-role-ref>
		<security-role-ref>
			<role-name>power-user</role-name>
		</security-role-ref>
		<security-role-ref>
			<role-name>user</role-name>
		</security-role-ref>
	</portlet>
	<portlet>
		<portlet-name>demo</portlet-name>
		<display-name>Demo</display-name>
		<portlet-class>com.test.Demo</portlet-class>
		<init-param>
			<name>view-template</name>
			<value>/html/demo/view.jsp</value>
		</init-param>
		<expiration-cache>0</expiration-cache>
		<supports>
			<mime-type>text/html</mime-type>
			<portlet-mode>view</portlet-mode>
		</supports>
		<portlet-info>
			<title>Demo</title>
			<short-title>Demo</short-title>
			<keywords></keywords>
		</portlet-info>
		<security-role-ref>
			<role-name>administrator</role-name>
		</security-role-ref>
		<security-role-ref>
			<role-name>guest</role-name>
		</security-role-ref>
		<security-role-ref>
			<role-name>power-user</role-name>
		</security-role-ref>
		<security-role-ref>
			<role-name>user</role-name>
		</security-role-ref>
	</portlet>
</portlet-app>